{
  "video_id": "zZxxDbLxEi4",
  "title": "Highlights | Argentina 3-1 Switzerland | FIFA World Cup 2026",
  "channel": "FIFA",
  "channel_id": "UCpcTrCXblq78GZrTUTLWeBw",
  "source_url": "https://www.youtube.com/watch?v=zZxxDbLxEi4",
  "upload_date": "2026-07-13",
  "duration_seconds": 130,
  "declared_license": null,
  "selected_source_format": "137+140",
  "selected_video": "H.264 1920x1080 30fps",
  "source_use": "local course-project presentation analysis",
  "redistribution_note": "Confirm permission/fair-use requirements before public redistribution."
}
